CHANGES.txt
LICENSE.txt
MANIFEST.in
README.txt
bootstrap.py
buildout.cfg
setup.py
src/p01/__init__.py
src/p01.kibana.egg-info/PKG-INFO
src/p01.kibana.egg-info/SOURCES.txt
src/p01.kibana.egg-info/dependency_links.txt
src/p01.kibana.egg-info/entry_points.txt
src/p01.kibana.egg-info/namespace_packages.txt
src/p01.kibana.egg-info/not-zip-safe
src/p01.kibana.egg-info/requires.txt
src/p01.kibana.egg-info/top_level.txt
src/p01/kibana/README.txt
src/p01/kibana/__init__.py
src/p01/kibana/backend.py
src/p01/kibana/client.py
src/p01/kibana/logger.py
src/p01/kibana/scripts.py
src/p01/kibana/server.py
src/p01/kibana/tests/__init__.py
src/p01/kibana/tests/checker.txt
src/p01/kibana/tests/test_client.py
src/p01/kibana/tests/test_docs.py
src/p01/kibana/tests/test_server.py