Metadata-Version: 2.1
Name: p01.kibana
Version: 0.9.1
Summary: Kibana logging client and server for logging without logstash
Home-page: http://pypi.python.org/pypi/p01.kibana
Author: Roger Ineichen, Projekt01 GmbH
Author-email: dev@projekt01.ch
License: ZPL 2.1
Keywords: Zope3 z3c p01 elasticsearch logstash kibana udp
Platform: UNKNOWN
Classifier: Development Status :: 5 - Production/Stable
Classifier: Environment :: Web Environment
Classifier: Intended Audience :: Developers
Classifier: License :: OSI Approved :: Zope Public License
Classifier: Programming Language :: Python
Classifier: Natural Language :: English
Classifier: Operating System :: OS Independent
Classifier: Topic :: Internet :: WWW/HTTP
Classifier: Framework :: Zope3
Provides-Extra: test
Provides-Extra: forwarder
Provides-Extra: geo
